cryptocurrencies_scraper/CurrencyService.py
cryptocurrencies_scraper/__init__.py
cryptocurrencies_scraper-0.0.3.dist-info/LICENSE.txt
cryptocurrencies_scraper-0.0.3.dist-info/METADATA
cryptocurrencies_scraper-0.0.3.dist-info/WHEEL
cryptocurrencies_scraper-0.0.3.dist-info/top_level.txt
cryptocurrencies_scraper-0.0.3.dist-info/RECORD
