Metadata-Version: 2.1
Name: cryptocurrencies-scraper
Version: 0.0.3
Summary: A simple scrapper that uses coin360.com and coinmarketcap.com apis to populate an instant local database
Home-page: https://github.com/Willena/python-crypto-currencies-scraper
Author: Guillaume VILLENA
Author-email: contact@guillaumevillena.fr
License: UNKNOWN
Project-URL: Bug Reports, https://github.com/Willena/python-crypto-currencies-scraper/issues
Project-URL: Funding, https://paypal.me/GuillaumeVillena
Project-URL: Say Thanks!, https://paypal.me/GuillaumeVillena
Project-URL: Source, https://github.com/Willena/python-crypto-currencies-scraper
Keywords: coin coin360 coinmarketcap api web scrapper
Platform: UNKNOWN
Classifier: Development Status :: 4 - Beta
Classifier: Intended Audience :: Developers
Classifier: Topic :: System :: Monitoring
Classifier: License :: OSI Approved :: MIT License
Classifier: Programming Language :: Python :: 2
Classifier: Programming Language :: Python :: 2.7
Classifier: Programming Language :: Python :: 3
Classifier: Programming Language :: Python :: 3.4
Classifier: Programming Language :: Python :: 3.5
Classifier: Programming Language :: Python :: 3.6
Classifier: Programming Language :: Python :: 3.7
Requires-Dist: requests
